pypinksign/__init__.py
pypinksign/pypinkseed.py
pypinksign/pypinksign.py
pypinksign/test_pinkSign.py
pypinksign-0.5.4.dist-info/licenses/LICENSE
pypinksign-0.5.4.dist-info/METADATA
pypinksign-0.5.4.dist-info/WHEEL
pypinksign-0.5.4.dist-info/top_level.txt
pypinksign-0.5.4.dist-info/RECORD
