Metadata-Version: 2.4
Name: pypinksign
Version: 0.5.4
Summary: Basic NPKI module.
Home-page: http://github.com/bandoche/PyPinkSign
Author: Sangjun Jung
Author-email: spamcoffee+pypinksign@gmail.com
License: MIT
Keywords: npki 공인인증서 공동인증서 korean pki certificate
Platform: OS Independent
Classifier: Development Status :: 4 - Beta
Classifier: Environment :: Console
Classifier: License :: OSI Approved :: MIT License
Classifier: Operating System :: OS Independent
Classifier: Programming Language :: Python :: 3 :: Only
Classifier: Programming Language :: Python :: 3.8
Classifier: Programming Language :: Python :: 3.9
Classifier: Programming Language :: Python :: 3.10
Classifier: Programming Language :: Python :: 3.11
Classifier: Programming Language :: Python :: 3.12
Classifier: Programming Language :: Python :: 3.13
License-File: LICENSE
Requires-Dist: pyasn1==0.6.1
Requires-Dist: cryptography>=46.0.3
Dynamic: author
Dynamic: author-email
Dynamic: classifier
Dynamic: description
Dynamic: home-page
Dynamic: keywords
Dynamic: license
Dynamic: license-file
Dynamic: platform
Dynamic: requires-dist
Dynamic: summary
